lakehouse_plumber-0.7.4.dist-info/licenses/LICENSE
lhp/__init__.py
lhp/bundle/__init__.py
lhp/bundle/databricks_yaml_manager.py
lhp/bundle/exceptions.py
lhp/bundle/manager.py
lhp/bundle/template_fetcher.py
lhp/cli/__init__.py
lhp/cli/main.py
lhp/cli/commands/__init__.py
lhp/cli/commands/base_command.py
lhp/cli/commands/dependencies_command.py
lhp/cli/commands/generate_command.py
lhp/cli/commands/init_command.py
lhp/cli/commands/list_commands.py
lhp/cli/commands/show_command.py
lhp/cli/commands/state_command.py
lhp/cli/commands/stats_command.py
lhp/cli/commands/validate_command.py
lhp/core/__init__.py
lhp/core/action_registry.py
lhp/core/base_generator.py
lhp/core/commands.py
lhp/core/config_field_validator.py
lhp/core/dependency_resolver.py
lhp/core/dlt_cdc_validators.py
lhp/core/factories.py
lhp/core/init_template_context.py
lhp/core/init_template_loader.py
lhp/core/layers.py
lhp/core/orchestrator.py
lhp/core/parallel_processor.py
lhp/core/project_config_loader.py
lhp/core/secret_validator.py
lhp/core/state_dependency_resolver.py
lhp/core/state_manager.py
lhp/core/state_models.py
lhp/core/strategies.py
lhp/core/template_engine.py
lhp/core/validator.py
lhp/core/services/__init__.py
lhp/core/services/code_generator.py
lhp/core/services/dependency_analyzer.py
lhp/core/services/dependency_output_manager.py
lhp/core/services/flowgroup_discoverer.py
lhp/core/services/flowgroup_processor.py
lhp/core/services/generation_planning_service.py
lhp/core/services/job_generator.py
lhp/core/services/job_name_validator.py
lhp/core/services/operational_metadata_service.py
lhp/core/services/pipeline_config_loader.py
lhp/core/services/pipeline_validator.py
lhp/core/state/__init__.py
lhp/core/state/dependency_tracker.py
lhp/core/state/state_analyzer.py
lhp/core/state/state_cleanup_service.py
lhp/core/state/state_persistence.py
lhp/core/validators/__init__.py
lhp/core/validators/base_validator.py
lhp/core/validators/load_validator.py
lhp/core/validators/table_creation_validator.py
lhp/core/validators/test_validator.py
lakehouse_plumber-0.7.4.dist-info/METADATA
lakehouse_plumber-0.7.4.dist-info/WHEEL
lakehouse_plumber-0.7.4.dist-info/entry_points.txt
lakehouse_plumber-0.7.4.dist-info/top_level.txt
lakehouse_plumber-0.7.4.dist-info/RECORD
