Metadata-Version: 2.4
Name: lakehouse-plumber
Version: 0.7.4
Summary: A framework for building and managing enterprise Lakeflow Spark Declaritive Pipelines
Author-email: Mehdi Modarressi <modarressi.mehdi@gmail.com>
License: Apache License
Project-URL: Homepage, https://github.com/Mmodarre/Lakehouse_Plumber
Project-URL: Documentation, https://lakehouse-plumber.readthedocs.io/
Project-URL: Repository, https://github.com/Mmodarre/Lakehouse_Plumber.git
Project-URL: Bug Tracker, https://github.com/Mmodarre/Lakehouse_Plumber/issues
Classifier: Development Status :: 4 - Beta
Classifier: Intended Audience :: Developers
Classifier: License :: OSI Approved :: Apache Software License
Classifier: Operating System :: OS Independent
Classifier: Programming Language :: Python :: 3
Classifier: Programming Language :: Python :: 3.11
Classifier: Programming Language :: Python :: 3.12
Classifier: Programming Language :: Python :: 3.13
Classifier: Topic :: Database
Classifier: Topic :: Scientific/Engineering
Classifier: Topic :: Software Development :: Libraries :: Python Modules
Requires-Python: >=3.11
License-File: LICENSE
Requires-Dist: click>=8.3.0
Requires-Dist: pyyaml>=6.0.3
Requires-Dist: ruamel.yaml>=0.19.0
Requires-Dist: jinja2>=3.0.0
Requires-Dist: rich>=14.0.0
Requires-Dist: pydantic>=2.12.0
Requires-Dist: jsonschema>=4.26.0
Requires-Dist: packaging>=23.2
Requires-Dist: black==26.1.0
Requires-Dist: networkx>=3.6.0
Provides-Extra: dev
Requires-Dist: pytest>=9.0.0; extra == "dev"
Requires-Dist: pytest-cov>=4.0.0; extra == "dev"
Requires-Dist: pytest-mock>=3.10.0; extra == "dev"
Requires-Dist: flake8>=6.0.0; extra == "dev"
Requires-Dist: black==26.1.0; extra == "dev"
Requires-Dist: isort>=5.12.0; extra == "dev"
Requires-Dist: mypy>=1.0.0; extra == "dev"
Requires-Dist: requests>=2.32.0; extra == "dev"
Provides-Extra: notebook
Requires-Dist: ipython>=7.0.0; extra == "notebook"
Requires-Dist: jupyter>=1.0.0; extra == "notebook"
Dynamic: license-file
